README.md
setup.py
netpy/__init__.py
netpy.egg-info/PKG-INFO
netpy.egg-info/SOURCES.txt
netpy.egg-info/dependency_links.txt
netpy.egg-info/requires.txt
netpy.egg-info/top_level.txt
netpy/modules/__init__.py
netpy/modules/module.py
netpy/modules/connections/Conv2D.py
netpy/modules/connections/FullConnection.py
netpy/modules/connections/_Conv.py
netpy/modules/connections/__init__.py
netpy/modules/connections/connection.py
netpy/modules/layers/__init__.py
netpy/modules/layers/layer.py
netpy/modules/layers/Linear/LinearLayer.py
netpy/modules/layers/Linear/ReluLayer.py
netpy/modules/layers/Linear/SigmoidLayer.py
netpy/modules/layers/Linear/SoftPlusLayer.py
netpy/modules/layers/Linear/SoftSignLayer.py
netpy/modules/layers/Linear/TanhLayer.py
netpy/modules/layers/Linear/__init__.py
netpy/nets/FeedForwardNet.py
netpy/nets/__init__.py
netpy/nets/net.py
netpy/teachers/BackPropTeacher.py
netpy/teachers/BackPropTeacherTest.py
netpy/teachers/BackPropTeacher_DVR.py
netpy/teachers/__init__.py
netpy/teachers/teacher.py
netpy/tools/__init__.py
netpy/tools/errors.py
netpy/tools/functions.py