Metadata-Version: 1.0
Name: netpy
Version: 0.0.0.1
Summary: Library for ML
Home-page: UNKNOWN
Author: nethub
Author-email: nethub@yandex.ru
License: UNKNOWN
Platform: UNKNOWN
